instarecsys/__init__.py
instarecsys/instarecsys.py
instarecsys/Data/df_sample.csv
instarecsys-0.1.3.dist-info/METADATA
instarecsys-0.1.3.dist-info/WHEEL
instarecsys-0.1.3.dist-info/top_level.txt
instarecsys-0.1.3.dist-info/RECORD
