Metadata-Version: 2.1
Name: instarecsys
Version: 0.1.3
Summary: recommend system for instacart dataset
Home-page: https://instarecsys.readthedocs.io/
Author: Alexander Surkov
Author-email: sanchelo2006@yandex.ru
License: MIT
Classifier: Intended Audience :: Developers
Classifier: License :: OSI Approved :: MIT License
Classifier: Programming Language :: Python
Classifier: Programming Language :: Python :: 3
Classifier: Programming Language :: Python :: 3.6
Classifier: Programming Language :: Python :: 3.7
Classifier: Programming Language :: Python :: 3.8
Classifier: Programming Language :: Python :: 3.9
Classifier: Operating System :: OS Independent
Requires-Dist: numpy
Requires-Dist: pandas
Requires-Dist: tqdm
Requires-Dist: pyarrow
